LICENSE
search_placeholder/__init__.py
search_placeholder/admin.py
search_placeholder/mixins.py
search_placeholder/templates/admin/search_form_plus.html
search_placeholder/templates/search_placeholder/change_list.html
search_placeholder/templatetags/__init__.py
search_placeholder/templatetags/search_with_placeholder.py
search_placeholder-0.2.0.dist-info/LICENSE
search_placeholder-0.2.0.dist-info/WHEEL
search_placeholder-0.2.0.dist-info/METADATA
search_placeholder-0.2.0.dist-info/RECORD
